 [
  {
    "callbackId": "ap-51107326-2417775978772-1-0",
    "origin": {
      "portalId": 51107326,
      "userId": null,
      "actionDefinitionId": 256332086,
      "actionDefinitionVersion": 5,
      "actionExecutionIndexIdentifier": {
        "enrollmentId": 2417775978772,
        "actionExecutionIndex": 0
      },
      "extensionDefinitionVersionId": 5,
      "extensionDefinitionId": 256332086
    },
    "context": {
      "workflowId": 1791344961,
      "actionId": 1,
      "actionExecutionIndexIdentifier": {
        "enrollmentId": 2417775978772,
        "actionExecutionIndex": 0
      },
      "source": "WORKFLOWS"
    },
    "object": { "objectId": 204513334098, "objectType": "CONTACT" },
    "fields": { "activity_timeline": "last" },
    "inputFields": { "activity_timeline": "last" },
    "typedInputs": {
      "activity_timeline": { "value": "last", "type": "STRING" }
    }
  },
  {
    "updatedAt": "2024-09-12T14:12:43.357Z",
    "createdAt": "2019-08-06T02:41:09.313Z",
    "name": "annualrevenue",
    "label": "Annual Revenue",
    "type": "string",
    "fieldType": "text",
    "description": "Annual company revenue",
    "groupName": "contactinformation",
    "options": [],
    "displayOrder": 22,
    "calculated": false,
    "externalOptions": false,
    "hasUniqueValue": false,
    "hidden": false,
    "hubspotDefined": true,
    "modificationMetadata": {
      "archivable": false,
      "readOnlyDefinition": false,
      "readOnlyValue": false
    },
    "formField": true,
    "dataSensitivity": "non_sensitive"
  }
]